FOMUserUtil/CleanupRoles.py
FOMUserUtil/FOMKeyCloak.py
FOMUserUtil/ForestClient.py
FOMUserUtil/__init__.py
FOMUserUtil/__main__.py
FOMUserUtil/command_line.py
FOMUserUtil/constants.py
FOMUserUtil/debug.py
FOMUserUtil/demoAddRole.py
FOMUserUtil/fomuser.py
FOMUserUtil/test_FOMKeyCloak.py
FOMUserUtil/test_forestClient.py
FOMUserUtil-0.0.13.dist-info/LICENSE.md
FOMUserUtil-0.0.13.dist-info/METADATA
FOMUserUtil-0.0.13.dist-info/WHEEL
FOMUserUtil-0.0.13.dist-info/entry_points.txt
FOMUserUtil-0.0.13.dist-info/top_level.txt
FOMUserUtil-0.0.13.dist-info/RECORD
